cyanide/__init__.py
cyanide/__main__.py
cyanide/app.py
cyanide/compat.py
cyanide/data.py
cyanide/fbi.py
cyanide/suite.py
cyanide/tasks.py
cyanide/templates.py
cyanide/bin/__init__.py
cyanide/bin/cyanide.py
cyanide/bin/vagrant.py
cyanide/suites/__init__.py
cyanide/suites/default.py
cyanide/tests/__init__.py
cyanide/tests/case.py
cyanide/vagrant/Vagrantfile
cyanide/vagrant/__init__.py
cyanide/vagrant/provision/celeryd-init.config
cyanide/vagrant/provision/provision.sh
cyanide-1.3.0.dist-info/DESCRIPTION.rst
cyanide-1.3.0.dist-info/METADATA
cyanide-1.3.0.dist-info/RECORD
cyanide-1.3.0.dist-info/WHEEL
cyanide-1.3.0.dist-info/entry_points.txt
cyanide-1.3.0.dist-info/metadata.json
cyanide-1.3.0.dist-info/top_level.txt
