Metadata-Version: 2.0
Name: cyanide
Version: 1.3.0
Summary: Celery stress testing and integration test support.
Home-page: https://github.com/celery/cyanide
Author: Ask Solem
Author-email: ask@celeryproject.org
License: BSD
Keywords: celery integration test suite
Platform: any
Classifier: Development Status :: 2 - Pre-Alpha
Classifier: License :: OSI Approved :: BSD License
Classifier: Programming Language :: Python
Classifier: Programming Language :: Python :: 2
Classifier: Programming Language :: Python :: 2.7
Classifier: Programming Language :: Python :: 3
Classifier: Programming Language :: Python :: 3.4
Classifier: Programming Language :: Python :: 3.5
Classifier: Programming Language :: Python :: Implementation :: CPython
Classifier: Programming Language :: Python :: Implementation :: PyPy
Classifier: Programming Language :: Python :: Implementation :: Jython
Classifier: Operating System :: OS Independent
Requires-Dist: python-vagrant
